AUTHORS.md
LICENSE
MANIFEST.in
README.md
setup.cfg
setup.py
poserbox/__init__.py
poserbox/nose_plugin.py
poserbox/poserbox.py
poserbox/utils.py
poserbox.egg-info/PKG-INFO
poserbox.egg-info/SOURCES.txt
poserbox.egg-info/dependency_links.txt
poserbox.egg-info/entry_points.txt
poserbox.egg-info/not-zip-safe
poserbox.egg-info/top_level.txt