Metadata-Version: 1.1
Name: poserbox
Version: 0.0.1
Summary: Run sandboxed Poser instance from a python application.
Home-page: http://github.com/ziadsawalha/poserbox
Author: Ziad Sawalha <ziad@sawalha.com>
Author-email: ziad@sawalha.com
License: Copyright 2014 Ziad Sawalha
